MANIFEST.in
README.txt
setup.py
docs/HISTORY.txt
docs/LICENSE.txt
src/silva/__init__.py
src/silva.core.cache.egg-info/PKG-INFO
src/silva.core.cache.egg-info/SOURCES.txt
src/silva.core.cache.egg-info/dependency_links.txt
src/silva.core.cache.egg-info/namespace_packages.txt
src/silva.core.cache.egg-info/not-zip-safe
src/silva.core.cache.egg-info/requires.txt
src/silva.core.cache.egg-info/top_level.txt
src/silva/core/__init__.py
src/silva/core/cache/__init__.py
src/silva/core/cache/beakercache.py
src/silva/core/cache/clientid.py
src/silva/core/cache/configure.zcml
src/silva/core/cache/descriptors.py
src/silva/core/cache/interfaces.py
src/silva/core/cache/lru.py
src/silva/core/cache/memcacheutils.py
src/silva/core/cache/store.py
src/silva/core/cache/testing.py
src/silva/core/cache/tests/__init__.py
src/silva/core/cache/tests/test_cache_manager.py
src/silva/core/cache/tests/test_descriptors.py
src/silva/core/cache/tests/test_memcacheslice.py