Metadata-Version: 1.1
Name: silva.core.cache
Version: 3.0.2
Summary: Caching sub-system for Silva CMS
Home-page: https://github.com/silvacms/silva.core.cache
Author: Infrae
Author-email: info@infrae.com
License: BSD
Keywords: zope2 cache silva
Platform: UNKNOWN
Classifier: Environment :: Web Environment
Classifier: Intended Audience :: Developers
Classifier: License :: OSI Approved :: Zope Public License
Classifier: Programming Language :: Python
Classifier: Topic :: Software Development :: Libraries :: Python Modules
Classifier: Framework :: Zope2
